pluginlib/__init__.py
plugin_library-0.0.0.dist-info/LICENSE
plugin_library-0.0.0.dist-info/METADATA
plugin_library-0.0.0.dist-info/WHEEL
plugin_library-0.0.0.dist-info/top_level.txt
plugin_library-0.0.0.dist-info/RECORD
