Metadata-Version: 2.1
Name: plugin-library
Version: 0.0.0
Summary: utility library to find and load configuration files
Home-page: https://github.com/utility-libraries/pluginlib-py
Author: PlayerG9
License: MIT
Project-URL: Organisation Github, https://github.com/utility-libraries
Project-URL: Homepage, https://github.com/utility-libraries/pluginlib-py/
Project-URL: Documentation, https://utility-libraries.github.io/pluginlib-py/
Project-URL: Bug Tracker, https://github.com/utility-libraries/pluginlib-py/issues
Classifier: Intended Audience :: Developers
Classifier: License :: OSI Approved :: MIT License
Classifier: Natural Language :: English
Classifier: Operating System :: OS Independent
Classifier: Programming Language :: Python :: 3
Classifier: Programming Language :: Python :: 3 :: Only
Classifier: Programming Language :: Python :: 3.7
Classifier: Programming Language :: Python :: 3.8
Classifier: Programming Language :: Python :: 3.9
Classifier: Programming Language :: Python :: 3.10
Classifier: Programming Language :: Python :: 3.11
Classifier: Programming Language :: Python :: 3.12
Classifier: Programming Language :: Python :: 3.13
Classifier: Topic :: Utilities
Requires-Python: >=3.6
License-File: LICENSE
Requires-Dist: pyyaml
